{
    "info": {
        "單位名稱": "台灣化學纖維股份有限公司",
        "發電案場": "台灣化學纖維股份有限公司一期",
        "能源類型": "太陽能",
        "案場地址": "嘉義縣新港鄉中洋村後厝仔中洋工業區1號",
        "裝置總容量": "499.125 kW"
    },
    "t-rec": {
        "2019": {
            "證書編號": "19SP0021-B019000001~205",
            "T-REC 最後憑證發放日期": "2020-01-14",
            "發電區間": "2019-09-06~2019-12-31",
            "再生能源設備查核報告": "認可",
            "再生能源發電量查證報告": "認可",
            "已移轉張數": "0",
            "剩餘張數": "205"
        },
        "2020": {
            "證書編號": "19SP0021-B020000001~464",
            "T-REC 最後憑證發放日期": "2020-10-15",
            "發電區間": "2019-12-31~2020-08-27",
            "再生能源設備查核報告": "認可",
            "再生能源發電量查證報告": "認可",
            "已移轉張數": "0",
            "剩餘張數": "464"
        },
        "2021": {
            "證書編號": "19SP0021-B021000001~872",
            "T-REC 最後憑證發放日期": "2022-02-15",
            "發電區間": "2020-08-27~2021-12-31",
            "再生能源設備查核報告": "認可",
            "再生能源發電量查證報告": "認可",
            "已移轉張數": "0",
            "剩餘張數": "872"
        },
        "2022": {
            "證書編號": "19SP0021-B022000001~630",
            "T-REC 最後憑證發放日期": "2023-02-18",
            "發電區間": "2021-12-31~2022-12-31",
            "再生能源設備查核報告": "認可",
            "再生能源發電量查證報告": "認可",
            "已移轉張數": "0",
            "剩餘張數": "630"
        },
        "2023": {
            "證書編號": "19SP0021-B023000001~624",
            "T-REC 最後憑證發放日期": "2024-02-19",
            "發電區間": "2022-12-31~2023-12-31",
            "再生能源設備查核報告": "認可",
            "再生能源發電量查證報告": "認可",
            "已移轉張數": "0",
            "剩餘張數": "624"
        },
        "2024": {
            "證書編號": "19SP0021-B024000001~46",
            "T-REC 最後憑證發放日期": "2024-03-18",
            "發電區間": "2023-12-31~2024-01-31",
            "再生能源設備查核報告": "認可",
            "再生能源發電量查證報告": "認可",
            "已移轉張數": "0",
            "剩餘張數": "46"
        }
    }
}