{
    "info": {
        "單位名稱": "天能綠電股份有限公司",
        "發電案場": "高雄大寮地面型太陽光電案場",
        "能源類型": "太陽能",
        "案場地址": "高雄市大寮區赤崁段6113、6114、6114-1、6161、6162、6163、6163-1、6164-1、6137-4地號",
        "裝置總容量": "994.56 kW"
    },
    "t-rec": {
        "2023": {
            "證書編號": "23SP0085-B023000001~441",
            "T-REC 最後憑證發放日期": "2024-02-20",
            "發電區間": "2023-08-01~2023-12-31",
            "再生能源設備查核報告": "認可",
            "再生能源發電量查證報告": "認可",
            "已移轉張數": "441",
            "剩餘張數": "0"
        },
        "2024": {
            "證書編號": "-",
            "T-REC 最後憑證發放日期": "-",
            "發電區間": "-",
            "再生能源設備查核報告": "認可",
            "再生能源發電量查證報告": "認可",
            "已移轉張數": "-",
            "剩餘張數": "-"
        }
    }
}